controller/__init__.py
controller/generic.py
controller/hero.py
controller/team.py
model/__init__.py
model/dto.py
model/models.py
repository/__init__.py
repository/base.py
service/__init__.py
service/base.py
util/__init__.py
util/database.py
herogentest_lib-0.1.8.dist-info/METADATA
herogentest_lib-0.1.8.dist-info/WHEEL
herogentest_lib-0.1.8.dist-info/top_level.txt
herogentest_lib-0.1.8.dist-info/RECORD
