Metadata-Version: 2.4
Name: herogentest-lib
Version: 0.1.8
Summary: Lib de heroes.
Home-page: https://github.com/Pedrordsm/FastAPI_learn.git
Author: Pedro Renã da Silva Moreira
Author-email: pedrorenanmoreira@gmail.com
Classifier: Programming Language :: Python :: 3
Classifier: License :: OSI Approved :: MIT License
Classifier: Operating System :: OS Independent
Requires-Python: >=3.8
Dynamic: author
Dynamic: author-email
Dynamic: classifier
Dynamic: description-content-type
Dynamic: home-page
Dynamic: requires-python
Dynamic: summary
